Metadata-Version: 2.1
Name: blur-image
Version: 0.1.0
Summary: A library to blurring images.
Home-page: https://github.com/onuratakan/blur_image
Author: Onur Atakan ULUSOY
Author-email: atadogan06@gmail.com
License: MIT
Platform: UNKNOWN
Requires-Python: >= 3
License-File: LICENSE
